LICENSE
MANIFEST.in
README.md
setup.py
django_rest_framework_docs.egg-info/PKG-INFO
django_rest_framework_docs.egg-info/SOURCES.txt
django_rest_framework_docs.egg-info/dependency_links.txt
django_rest_framework_docs.egg-info/requires.txt
django_rest_framework_docs.egg-info/top_level.txt
rest_framework_docs/__init__.py
rest_framework_docs/docs.py
rest_framework_docs/tests.py
rest_framework_docs/urls.py
rest_framework_docs/views.py
rest_framework_docs/templates/rest_framework_docs/docs.html